{"resourceType": "StructureDefinition", "id": "AttributionParticuliere", "url": "https://interop.esante.gouv.fr/ig/fhir/mos/StructureDefinition/AttributionParticuliere", "name": "AttributionParticuliere", "status": "draft", "kind": "logical", "abstract": false, "type": "https://interop.esante.gouv.fr/ig/fhir/mos/StructureDefinition/AttributionParticuliere", "baseDefinition": "http://hl7.org/fhir/StructureDefinition/Base", "derivation": "specialization", "differential": {"element": [{"id": "AttributionParticuliere", "path": "AttributionParticuliere", "definition": " Activités ponctuelles du professionnel de type expertise.", "short": " Activités ponctuelles du professionnel de type expertise.", "min": 0, "max": "*", "type": [{"code": "Element"}]}, {"id": "AttributionParticuliere.attributionParticuliere", "path": "AttributionParticuliere.attributionParticuliere", "definition": " Attribution particulière.Par exemple : **Agrément : Autorisation d’un médecin généraliste ou spécialiste, formalisée par un agrément, à figurer sur une liste départementale établie par le Préfet sur proposition du directeur départemental de l'action sanitaire et sociale et après avis du conseil départemental de l'ordre des médecins et des syndicats départementaux des médecins.", "short": " Attribution particulière.Par exemple : **Agrément : Autorisation d’un médecin généraliste ou spécialiste, formalisée par un agrément, à figurer sur une liste départementale établie par le Préfet sur proposition du directeur départemental de l'action sanitaire et sociale et après avis du conseil départemental de l'ordre des médecins et des syndicats départementaux des médecins.", "min": 0, "max": "1", "type": [{"code": "Coding"}], "binding": {"strength": "preferred", "valueSet": "https://interop.esante.gouv.fr/ig/fhir/mos/ValueSet/AttributionParticuliere-vs"}}, {"id": "AttributionParticuliere.dateDebutReconnaissance", "path": "AttributionParticuliere.dateDebutReconnaissance", "definition": " Date à partir de laquelle l'attribution particulière prend effet.", "short": " Date à partir de laquelle l'attribution particulière prend effet.", "min": 0, "max": "1", "type": [{"code": "date"}]}, {"id": "AttributionParticuliere.dateAbandon", "path": "AttributionParticuliere.dateAbandon", "definition": " Date à laquelle le professionnel ne veut plus faire apparaître cette attribution.", "short": " Date à laquelle le professionnel ne veut plus faire apparaître cette attribution.", "min": 0, "max": "1", "type": [{"code": "date"}]}]}}