{
  "date" : "Thu, 23 Oct, 2025 12:51:24 +0000",
  "doco" : "For each file: start is seconds after start activity occurred. Length = milliseconds activity took",
  "files" : [
    {
      "name" : "/fsh-generated/resources/ImplementationGuide-ans.fr.mos.json",
      "size" : 33402,
      "processes" : [
        {
          "activity" : "load",
          "start" : 42,
          "length" : 17
        },
        {
          "activity" : "checkR4R4B",
          "start" : 43,
          "length" : 18
        },
        {
          "activity" : "generateNarratives",
          "start" : 43,
          "length" : 56
        },
        {
          "activity" : "validate",
          "start" : 71,
          "length" : 2838
        },
        {
          "activity" : "checkURLsUnique",
          "start" : 74,
          "length" : 1
        },
        {
          "activity" : "generate1",
          "start" : 74,
          "length" : 154
        },
        {
          "activity" : "generate2",
          "start" : 80,
          "length" : 392
        },
        {
          "activity" : "generateValidationPack",
          "start" : 108,
          "length" : 18
        },
        {
          "activity" : "scanExamplesForR5",
          "start" : 123,
          "length" : 1
        }
      ]
    },
    {
      "name" : "fsh-generated/resources/StructureDefinition-Adresse.json",
      "size" : 26297,
      "processes" : [
        {
          "activity" : "loadResources",
          "start" : 42,
          "length" : 6
        },
        {
          "activity" : "load",
          "start" : 42,
          "length" : 14
        },
        {
          "activity" : "generateSnapshots",
          "start" : 42,
          "length" : 16
        },
        {
          "activity" : "load-configure",
          "start" : 43,
          "length" : 1
        },
        {
          "activity" : "generateNarratives",
          "start" : 43,
          "length" : 1894
        },
        {
          "activity" : "validate",
          "start" : 56,
          "length" : 1008
        },
        {
          "activity" : "scanForUsageStats",
          "start" : 74,
          "length" : 1
        },
        {
          "activity" : "generate1",
          "start" : 74,
          "length" : 167
        },
        {
          "activity" : "generate2",
          "start" : 80,
          "length" : 818
        },
        {
          "activity" : "generate2",
          "start" : 94,
          "length" : 417
        },
        {
          "activity" : "generateValidationPack",
          "start" : 109,
          "length" : 9
        }
      ]
    },
    {
      "name" : "fsh-generated/resources/StructureDefinition-Attestation.json",
      "size" : 2517,
      "processes" : [
        {
          "activity" : "loadResources",
          "start" : 42,
          "length" : 3
        },
        {
          "activity" : "load",
          "start" : 42,
          "length" : 7
        },
        {
          "activity" : "generateSnapshots",
          "start" : 42,
          "length" : 30
        },
        {
          "activity" : "generateNarratives",
          "start" : 45,
          "length" : 181
        },
        {
          "activity" : "validate",
          "start" : 57,
          "length" : 811
        },
        {
          "activity" : "generate1",
          "start" : 74,
          "length" : 35
        },
        {
          "activity" : "generate2",
          "start" : 81,
          "length" : 131
        },
        {
          "activity" : "generate2",
          "start" : 95,
          "length" : 49
        },
        {
          "activity" : "generateValidationPack",
          "start" : 109,
          "length" : 2
        }
      ]
    },
    {
      "name" : "fsh-generated/resources/StructureDefinition-AutreDiplomeObtenu.json",
      "size" : 2128,
      "processes" : [
        {
          "activity" : "loadResources",
          "start" : 42,
          "length" : 3
        },
        {
          "activity" : "load",
          "start" : 42,
          "length" : 4
        },
        {
          "activity" : "generateSnapshots",
          "start" : 42,
          "length" : 15
        },
        {
          "activity" : "generateNarratives",
          "start" : 45,
          "length" : 186
        },
        {
          "activity" : "validate",
          "start" : 58,
          "length" : 312
        },
        {
          "activity" : "generate1",
          "start" : 74,
          "length" : 36
        },
        {
          "activity" : "generate2",
          "start" : 81,
          "length" : 101
        },
        {
          "activity" : "generate2",
          "start" : 95,
          "length" : 43
        },
        {
          "activity" : "generateValidationPack",
          "start" : 109,
          "length" : 1
        }
      ]
    },
    {
      "name" : "fsh-generated/resources/StructureDefinition-BoiteLettreMSS.json",
      "size" : 6930,
      "processes" : [
        {
          "activity" : "loadResources",
          "start" : 42,
          "length" : 4
        },
        {
          "activity" : "load",
          "start" : 42,
          "length" : 5
        },
        {
          "activity" : "generateSnapshots",
          "start" : 42,
          "length" : 16
        },
        {
          "activity" : "generateNarratives",
          "start" : 46,
          "length" : 178
        },
        {
          "activity" : "validate",
          "start" : 58,
          "length" : 338
        },
        {
          "activity" : "generate1",
          "start" : 74,
          "length" : 48
        },
        {
          "activity" : "generate2",
          "start" : 81,
          "length" : 93
        },
        {
          "activity" : "generate2",
          "start" : 95,
          "length" : 54
        },
        {
          "activity" : "generateValidationPack",
          "start" : 109,
          "length" : 3
        },
        {
          "activity" : "scanExamplesForR5",
          "start" : 123,
          "length" : 1
        }
      ]
    },
    {
      "name" : "fsh-generated/resources/StructureDefinition-CapaciteDiplome.json",
      "size" : 3654,
      "processes" : [
        {
          "activity" : "loadResources",
          "start" : 42,
          "length" : 3
        },
        {
          "activity" : "load",
          "start" : 42,
          "length" : 3
        },
        {
          "activity" : "generateSnapshots",
          "start" : 42,
          "length" : 14
        },
        {
          "activity" : "generateNarratives",
          "start" : 46,
          "length" : 236
        },
        {
          "activity" : "validate",
          "start" : 58,
          "length" : 283
        },
        {
          "activity" : "generate1",
          "start" : 74,
          "length" : 31
        },
        {
          "activity" : "generate2",
          "start" : 81,
          "length" : 80
        },
        {
          "activity" : "generate2",
          "start" : 95,
          "length" : 45
        },
        {
          "activity" : "generateValidationPack",
          "start" : 109,
          "length" : 1
        }
      ]
    },
    {
      "name" : "fsh-generated/resources/StructureDefinition-CapaciteSavoirfaire.json",
      "size" : 2706,
      "processes" : [
        {
          "activity" : "loadResources",
          "start" : 42,
          "length" : 4
        },
        {
          "activity" : "load",
          "start" : 42,
          "length" : 3
        },
        {
          "activity" : "generateSnapshots",
          "start" : 42,
          "length" : 33
        },
        {
          "activity" : "generateNarratives",
          "start" : 46,
          "length" : 8
        },
        {
          "activity" : "validate",
          "start" : 59,
          "length" : 286
        },
        {
          "activity" : "generate1",
          "start" : 74,
          "length" : 28
        },
        {
          "activity" : "generate2",
          "start" : 82,
          "length" : 69
        },
        {
          "activity" : "generate2",
          "start" : 95,
          "length" : 41
        },
        {
          "activity" : "generateValidationPack",
          "start" : 109,
          "length" : 2
        }
      ]
    },
    {
      "name" : "fsh-generated/resources/StructureDefinition-CertificatEtudeSpeciale.json",
      "size" : 2525,
      "processes" : [
        {
          "activity" : "loadResources",
          "start" : 42,
          "length" : 3
        },
        {
          "activity" : "load",
          "start" : 42,
          "length" : 3
        },
        {
          "activity" : "generateSnapshots",
          "start" : 42,
          "length" : 17
        },
        {
          "activity" : "generateNarratives",
          "start" : 46,
          "length" : 170
        },
        {
          "activity" : "validate",
          "start" : 59,
          "length" : 302
        },
        {
          "activity" : "generate1",
          "start" : 74,
          "length" : 24
        },
        {
          "activity" : "generate2",
          "start" : 82,
          "length" : 62
        },
        {
          "activity" : "generate2",
          "start" : 95,
          "length" : 38
        },
        {
          "activity" : "generateValidationPack",
          "start" : 109,
          "length" : 1
        }
      ]
    },
    {
      "name" : "fsh-generated/resources/StructureDefinition-Competence.json",
      "size" : 5614,
      "processes" : [
        {
          "activity" : "loadResources",
          "start" : 42,
          "length" : 3
        },
        {
          "activity" : "load",
          "start" : 42,
          "length" : 4
        },
        {
          "activity" : "generateSnapshots",
          "start" : 42,
          "length" : 14
        },
        {
          "activity" : "load-configure",
          "start" : 43,
          "length" : 1
        },
        {
          "activity" : "generateNarratives",
          "start" : 46,
          "length" : 7
        },
        {
          "activity" : "validate",
          "start" : 59,
          "length" : 37
        },
        {
          "activity" : "generate1",
          "start" : 74,
          "length" : 34
        },
        {
          "activity" : "generate2",
          "start" : 82,
          "length" : 71
        },
        {
          "activity" : "generate2",
          "start" : 95,
          "length" : 42
        },
        {
          "activity" : "generateValidationPack",
          "start" : 109,
          "length" : 2
        }
      ]
    },
    {
      "name" : "fsh-generated/resources/StructureDefinition-CompetenceExclusive.json",
      "size" : 2564,
      "processes" : [
        {
          "activity" : "loadResources",
          "start" : 42,
          "length" : 3
        },
        {
          "activity" : "load",
          "start" : 42,
          "length" : 3
        },
        {
          "activity" : "generateSnapshots",
          "start" : 42,
          "length" : 17
        },
        {
          "activity" : "generateNarratives",
          "start" : 46,
          "length" : 5
        },
        {
          "activity" : "validate",
          "start" : 59,
          "length" : 34
        },
        {
          "activity" : "generate1",
          "start" : 74,
          "length" : 27
        },
        {
          "activity" : "generate2",
          "start" : 82,
          "length" : 59
        },
        {
          "activity" : "generate2",
          "start" : 95,
          "length" : 41
        },
        {
          "activity" : "generateValidationPack",
          "start" : 109,
          "length" : 2
        }
      ]
    },
    {
      "name" : "fsh-generated/resources/StructureDefinition-CompetenceMetier.json",
      "size" : 4627,
      "processes" : [
        {
          "activity" : "loadResources",
          "start" : 42,
          "length" : 3
        },
        {
          "activity" : "load",
          "start" : 42,
          "length" : 4
        },
        {
          "activity" : "generateSnapshots",
          "start" : 42,
          "length" : 15
        },
        {
          "activity" : "generateNarratives",
          "start" : 46,
          "length" : 170
        },
        {
          "activity" : "validate",
          "start" : 59,
          "length" : 311
        },
        {
          "activity" : "generate1",
          "start" : 74,
          "length" : 32
        },
        {
          "activity" : "generate2",
          "start" : 82,
          "length" : 62
        },
        {
          "activity" : "generate2",
          "start" : 95,
          "length" : 38
        },
        {
          "activity" : "makeDependencies",
          "start" : 97,
          "length" : 1
        },
        {
          "activity" : "generateValidationPack",
          "start" : 109,
          "length" : 7
        }
      ]
    },
    {
      "name" : "fsh-generated/resources/StructureDefinition-DESC1.json",
      "size" : 4115,
      "processes" : [
        {
          "activity" : "loadResources",
          "start" : 42,
          "length" : 3
        },
        {
          "activity" : "load",
          "start" : 42,
          "length" : 4
        },
        {
          "activity" : "generateSnapshots",
          "start" : 43,
          "length" : 18
        },
        {
          "activity" : "generateNarratives",
          "start" : 46,
          "length" : 171
        },
        {
          "activity" : "validate",
          "start" : 59,
          "length" : 292
        },
        {
          "activity" : "scanForUsageStats",
          "start" : 74,
          "length" : 1
        },
        {
          "activity" : "generate1",
          "start" : 75,
          "length" : 31
        },
        {
          "activity" : "generate2",
          "start" : 82,
          "length" : 67
        },
        {
          "activity" : "generate2",
          "start" : 95,
          "length" : 37
        },
        {
          "activity" : "generateValidationPack",
          "start" : 109,
          "length" : 2
        }
      ]
    },
    {
      "name" : "fsh-generated/resources/StructureDefinition-DESC2.json",
      "size" : 2270,
      "processes" : [
        {
          "activity" : "loadResources",
          "start" : 42,
          "length" : 3
        },
        {
          "activity" : "load",
          "start" : 42,
          "length" : 3
        },
        {
          "activity" : "generateSnapshots",
          "start" : 43,
          "length" : 19
        },
        {
          "activity" : "generateNarratives",
          "start" : 47,
          "length" : 171
        },
        {
          "activity" : "validate",
          "start" : 60,
          "length" : 298
        },
        {
          "activity" : "generate1",
          "start" : 75,
          "length" : 25
        },
        {
          "activity" : "generate2",
          "start" : 82,
          "length" : 60
        },
        {
          "activity" : "generate2",
          "start" : 95,
          "length" : 37
        },
        {
          "activity" : "generateValidationPack",
          "start" : 109,
          "length" : 1
        },
        {
          "activity" : "scanProfilesForR5",
          "start" : 123,
          "length" : 1
        }
      ]
    },
    {
      "name" : "fsh-generated/resources/StructureDefinition-DESCNonQualifiant.json",
      "size" : 2657,
      "processes" : [
        {
          "activity" : "loadResources",
          "start" : 42,
          "length" : 2
        },
        {
          "activity" : "load",
          "start" : 42,
          "length" : 3
        },
        {
          "activity" : "generateSnapshots",
          "start" : 43,
          "length" : 16
        },
        {
          "activity" : "generateNarratives",
          "start" : 47,
          "length" : 5
        },
        {
          "activity" : "validate",
          "start" : 60,
          "length" : 28
        },
        {
          "activity" : "generate1",
          "start" : 75,
          "length" : 29
        },
        {
          "activity" : "generate2",
          "start" : 82,
          "length" : 55
        },
        {
          "activity" : "generate2",
          "start" : 95,
          "length" : 36
        },
        {
          "activity" : "generateValidationPack",
          "start" : 109,
          "length" : 1
        }
      ]
    },
    {
      "name" : "fsh-generated/resources/StructureDefinition-Diplome.json",
      "size" : 4264,
      "processes" : [
        {
          "activity" : "loadResources",
          "start" : 42,
          "length" : 4
        },
        {
          "activity" : "load",
          "start" : 42,
          "length" : 4
        },
        {
          "activity" : "generateNarratives",
          "start" : 47,
          "length" : 334
        },
        {
          "activity" : "validate",
          "start" : 60,
          "length" : 42
        },
        {
          "activity" : "generate1",
          "start" : 75,
          "length" : 34
        },
        {
          "activity" : "generate2",
          "start" : 82,
          "length" : 60
        },
        {
          "activity" : "generate2",
          "start" : 95,
          "length" : 35
        },
        {
          "activity" : "generateValidationPack",
          "start" : 109,
          "length" : 2
        }
      ]
    },
    {
      "name" : "fsh-generated/resources/StructureDefinition-DiplomeDeuxiemeCycleNonQualifiant.json",
      "size" : 2478,
      "processes" : [
        {
          "activity" : "loadResources",
          "start" : 42,
          "length" : 2
        },
        {
          "activity" : "load",
          "start" : 42,
          "length" : 5
        },
        {
          "activity" : "generateSnapshots",
          "start" : 43,
          "length" : 25
        },
        {
          "activity" : "generateNarratives",
          "start" : 47,
          "length" : 178
        },
        {
          "activity" : "validate",
          "start" : 60,
          "length" : 291
        },
        {
          "activity" : "checkConformanceResources",
          "start" : 74,
          "length" : 1
        },
        {
          "activity" : "generate1",
          "start" : 75,
          "length" : 25
        },
        {
          "activity" : "generate2",
          "start" : 82,
          "length" : 52
        },
        {
          "activity" : "generate2",
          "start" : 95,
          "length" : 32
        },
        {
          "activity" : "generateValidationPack",
          "start" : 109,
          "length" : 1
        }
      ]
    },
    {
      "name" : "fsh-generated/resources/StructureDefinition-DiplomeDivers.json",
      "size" : 2148,
      "processes" : [
        {
          "activity" : "loadResources",
          "start" : 42,
          "length" : 4
        },
        {
          "activity" : "load",
          "start" : 42,
          "length" : 3
        },
        {
          "activity" : "generateSnapshots",
          "start" : 43,
          "length" : 16
        },
        {
          "activity" : "generateNarratives",
          "start" : 47,
          "length" : 185
        },
        {
          "activity" : "validate",
          "start" : 60,
          "length" : 279
        },
        {
          "activity" : "generate1",
          "start" : 75,
          "length" : 23
        },
        {
          "activity" : "generate2",
          "start" : 82,
          "length" : 52
        },
        {
          "activity" : "generate2",
          "start" : 95,
          "length" : 33
        },
        {
          "activity" : "generateValidationPack",
          "start" : 109,
          "length" : 2
        }
      ]
    },
    {
      "name" : "fsh-generated/resources/StructureDefinition-DiplomeEEE.json",
      "size" : 3030,
      "processes" : [
        {
          "activity" : "loadResources",
          "start" : 42,
          "length" : 2
        },
        {
          "activity" : "load",
          "start" : 42,
          "length" : 3
        },
        {
          "activity" : "generateSnapshots",
          "start" : 43,
          "length" : 14
        },
        {
          "activity" : "generateNarratives",
          "start" : 47,
          "length" : 184
        },
        {
          "activity" : "validate",
          "start" : 61,
          "length" : 285
        },
        {
          "activity" : "generate1",
          "start" : 75,
          "length" : 26
        },
        {
          "activity" : "generate2",
          "start" : 82,
          "length" : 55
        },
        {
          "activity" : "generate2",
          "start" : 95,
          "length" : 32
        },
        {
          "activity" : "generateValidationPack",
          "start" : 109,
          "length" : 1
        }
      ]
    },
    {
      "name" : "fsh-generated/resources/StructureDefinition-DiplomeEES.json",
      "size" : 3169,
      "processes" : [
        {
          "activity" : "loadResources",
          "start" : 42,
          "length" : 3
        },
        {
          "activity" : "load",
          "start" : 42,
          "length" : 3
        },
        {
          "activity" : "generateSnapshots",
          "start" : 43,
          "length" : 19
        },
        {
          "activity" : "load-configure",
          "start" : 43,
          "length" : 1
        },
        {
          "activity" : "generateNarratives",
          "start" : 48,
          "length" : 186
        },
        {
          "activity" : "validate",
          "start" : 61,
          "length" : 299
        },
        {
          "activity" : "generate1",
          "start" : 75,
          "length" : 27
        },
        {
          "activity" : "generate2",
          "start" : 82,
          "length" : 64
        },
        {
          "activity" : "generate2",
          "start" : 95,
          "length" : 32
        },
        {
          "activity" : "generateValidationPack",
          "start" : 109,
          "length" : 1
        }
      ]
    },
    {
      "name" : "fsh-generated/resources/StructureDefinition-DiplomeEtat.json",
      "size" : 4248,
      "processes" : [
        {
          "activity" : "loadResources",
          "start" : 42,
          "length" : 3
        },
        {
          "activity" : "load",
          "start" : 42,
          "length" : 5
        },
        {
          "activity" : "generateSnapshots",
          "start" : 43,
          "length" : 7
        },
        {
          "activity" : "generateNarratives",
          "start" : 48,
          "length" : 172
        },
        {
          "activity" : "validate",
          "start" : 61,
          "length" : 302
        },
        {
          "activity" : "generate1",
          "start" : 75,
          "length" : 38
        },
        {
          "activity" : "generate2",
          "start" : 82,
          "length" : 59
        },
        {
          "activity" : "generate2",
          "start" : 95,
          "length" : 48
        },
        {
          "activity" : "generateValidationPack",
          "start" : 109,
          "length" : 2
        }
      ]
    },
    {
      "name" : "fsh-generated/resources/StructureDefinition-DiplomeEtudeSpecialisee.json",
      "size" : 5100,
      "processes" : [
        {
          "activity" : "loadResources",
          "start" : 42,
          "length" : 3
        },
        {
          "activity" : "load",
          "start" : 42,
          "length" : 5
        },
        {
          "activity" : "generateSnapshots",
          "start" : 43,
          "length" : 4
        },
        {
          "activity" : "generateNarratives",
          "start" : 48,
          "length" : 172
        },
        {
          "activity" : "validate",
          "start" : 62,
          "length" : 297
        },
        {
          "activity" : "generate1",
          "start" : 75,
          "length" : 31
        },
        {
          "activity" : "generate2",
          "start" : 82,
          "length" : 55
        },
        {
          "activity" : "generate2",
          "start" : 95,
          "length" : 39
        },
        {
          "activity" : "generateValidationPack",
          "start" : 109,
          "length" : 3
        }
      ]
    },
    {
      "name" : "fsh-generated/resources/StructureDefinition-DiplomeUniversitaire.json",
      "size" : 3397,
      "processes" : [
        {
          "activity" : "loadResources",
          "start" : 42,
          "length" : 3
        },
        {
          "activity" : "load",
          "start" : 42,
          "length" : 3
        },
        {
          "activity" : "generateSnapshots",
          "start" : 43,
          "length" : 4
        },
        {
          "activity" : "generateNarratives",
          "start" : 48,
          "length" : 170
        },
        {
          "activity" : "validate",
          "start" : 62,
          "length" : 289
        },
        {
          "activity" : "processProvenanceDetails",
          "start" : 74,
          "length" : 1
        },
        {
          "activity" : "generate1",
          "start" : 75,
          "length" : 28
        },
        {
          "activity" : "generate2",
          "start" : 82,
          "length" : 55
        },
        {
          "activity" : "generate2",
          "start" : 95,
          "length" : 32
        },
        {
          "activity" : "generateValidationPack",
          "start" : 109,
          "length" : 1
        }
      ]
    },
    {
      "name" : "fsh-generated/resources/StructureDefinition-DroitExerciceComplementaire.json",
      "size" : 1956,
      "processes" : [
        {
          "activity" : "loadResources",
          "start" : 42,
          "length" : 3
        },
        {
          "activity" : "load",
          "start" : 42,
          "length" : 3
        },
        {
          "activity" : "generateSnapshots",
          "start" : 43,
          "length" : 5
        },
        {
          "activity" : "generateNarratives",
          "start" : 48,
          "length" : 9
        },
        {
          "activity" : "validate",
          "start" : 62,
          "length" : 21
        },
        {
          "activity" : "generate1",
          "start" : 75,
          "length" : 24
        },
        {
          "activity" : "generate2",
          "start" : 83,
          "length" : 53
        },
        {
          "activity" : "generate2",
          "start" : 95,
          "length" : 31
        },
        {
          "activity" : "generateValidationPack",
          "start" : 109,
          "length" : 1
        }
      ]
    },
    {
      "name" : "fsh-generated/resources/StructureDefinition-ExerciceProfessionnel.json",
      "size" : 18088,
      "processes" : [
        {
          "activity" : "loadResources",
          "start" : 42,
          "length" : 4
        },
        {
          "activity" : "load",
          "start" : 42,
          "length" : 7
        },
        {
          "activity" : "generateSnapshots",
          "start" : 43,
          "length" : 12
        },
        {
          "activity" : "generateNarratives",
          "start" : 48,
          "length" : 1542
        },
        {
          "activity" : "validate",
          "start" : 62,
          "length" : 2460
        },
        {
          "activity" : "generate1",
          "start" : 75,
          "length" : 117
        },
        {
          "activity" : "generate2",
          "start" : 83,
          "length" : 143
        },
        {
          "activity" : "generate2",
          "start" : 95,
          "length" : 91
        },
        {
          "activity" : "generateValidationPack",
          "start" : 109,
          "length" : 8
        }
      ]
    },
    {
      "name" : "fsh-generated/resources/StructureDefinition-FonctionQualifiee.json",
      "size" : 3727,
      "processes" : [
        {
          "activity" : "loadResources",
          "start" : 42,
          "length" : 3
        },
        {
          "activity" : "load",
          "start" : 42,
          "length" : 3
        },
        {
          "activity" : "generateSnapshots",
          "start" : 43,
          "length" : 5
        },
        {
          "activity" : "generateNarratives",
          "start" : 50,
          "length" : 5
        },
        {
          "activity" : "validate",
          "start" : 65,
          "length" : 35
        },
        {
          "activity" : "generate1",
          "start" : 75,
          "length" : 28
        },
        {
          "activity" : "generate2",
          "start" : 83,
          "length" : 65
        },
        {
          "activity" : "generate2",
          "start" : 96,
          "length" : 30
        },
        {
          "activity" : "generateValidationPack",
          "start" : 109,
          "length" : 3
        }
      ]
    },
    {
      "name" : "fsh-generated/resources/StructureDefinition-FormationSpecialiseeTransversale.json",
      "size" : 3669,
      "processes" : [
        {
          "activity" : "loadResources",
          "start" : 42,
          "length" : 3
        },
        {
          "activity" : "load",
          "start" : 42,
          "length" : 5
        },
        {
          "activity" : "generateSnapshots",
          "start" : 43,
          "length" : 8
        },
        {
          "activity" : "generateNarratives",
          "start" : 50,
          "length" : 170
        },
        {
          "activity" : "validate",
          "start" : 65,
          "length" : 282
        },
        {
          "activity" : "generate1",
          "start" : 75,
          "length" : 28
        },
        {
          "activity" : "generate2",
          "start" : 83,
          "length" : 70
        },
        {
          "activity" : "generate2",
          "start" : 96,
          "length" : 29
        },
        {
          "activity" : "generateValidationPack",
          "start" : 109,
          "length" : 3
        }
      ]
    },
    {
      "name" : "fsh-generated/resources/StructureDefinition-Horaire.json",
      "size" : 6692,
      "processes" : [
        {
          "activity" : "loadResources",
          "start" : 42,
          "length" : 3
        },
        {
          "activity" : "load",
          "start" : 42,
          "length" : 4
        },
        {
          "activity" : "generateSnapshots",
          "start" : 43,
          "length" : 8
        },
        {
          "activity" : "generateNarratives",
          "start" : 50,
          "length" : 183
        },
        {
          "activity" : "validate",
          "start" : 65,
          "length" : 303
        },
        {
          "activity" : "generate1",
          "start" : 75,
          "length" : 49
        },
        {
          "activity" : "generate2",
          "start" : 83,
          "length" : 91
        },
        {
          "activity" : "generate2",
          "start" : 96,
          "length" : 41
        },
        {
          "activity" : "generateValidationPack",
          "start" : 109,
          "length" : 4
        },
        {
          "activity" : "scanExamplesForR5",
          "start" : 123,
          "length" : 1
        }
      ]
    },
    {
      "name" : "fsh-generated/resources/StructureDefinition-LangueParlee.json",
      "size" : 1691,
      "processes" : [
        {
          "activity" : "loadResources",
          "start" : 42,
          "length" : 3
        },
        {
          "activity" : "load",
          "start" : 42,
          "length" : 4
        },
        {
          "activity" : "generateSnapshots",
          "start" : 43,
          "length" : 4
        },
        {
          "activity" : "generateNarratives",
          "start" : 50,
          "length" : 178
        },
        {
          "activity" : "validate",
          "start" : 65,
          "length" : 276
        },
        {
          "activity" : "generate1",
          "start" : 75,
          "length" : 22
        },
        {
          "activity" : "generate2",
          "start" : 83,
          "length" : 59
        },
        {
          "activity" : "generate2",
          "start" : 96,
          "length" : 19
        },
        {
          "activity" : "generateValidationPack",
          "start" : 109,
          "length" : 1
        }
      ]
    },
    {
      "name" : "fsh-generated/resources/StructureDefinition-OrientationParticuliere.json",
      "size" : 2362,
      "processes" : [
        {
          "activity" : "loadResources",
          "start" : 42,
          "length" : 3
        },
        {
          "activity" : "load",
          "start" : 42,
          "length" : 3
        },
        {
          "activity" : "generateSnapshots",
          "start" : 43,
          "length" : 6
        },
        {
          "activity" : "load-configure",
          "start" : 43,
          "length" : 1
        },
        {
          "activity" : "generateNarratives",
          "start" : 50,
          "length" : 5
        },
        {
          "activity" : "validate",
          "start" : 66,
          "length" : 24
        },
        {
          "activity" : "scanForUsageStats",
          "start" : 74,
          "length" : 1
        },
        {
          "activity" : "generate1",
          "start" : 75,
          "length" : 24
        },
        {
          "activity" : "generate2",
          "start" : 83,
          "length" : 67
        },
        {
          "activity" : "generate2",
          "start" : 96,
          "length" : 19
        },
        {
          "activity" : "generateValidationPack",
          "start" : 109,
          "length" : 3
        }
      ]
    },
    {
      "name" : "fsh-generated/resources/StructureDefinition-PersonnePhysique.json",
      "size" : 24351,
      "processes" : [
        {
          "activity" : "loadResources",
          "start" : 42,
          "length" : 4
        },
        {
          "activity" : "load",
          "start" : 42,
          "length" : 8
        },
        {
          "activity" : "generateSnapshots",
          "start" : 43,
          "length" : 14
        },
        {
          "activity" : "generateNarratives",
          "start" : 50,
          "length" : 671
        },
        {
          "activity" : "validate",
          "start" : 66,
          "length" : 1178
        },
        {
          "activity" : "generate1",
          "start" : 75,
          "length" : 138
        },
        {
          "activity" : "generate2",
          "start" : 83,
          "length" : 176
        },
        {
          "activity" : "generate2",
          "start" : 96,
          "length" : 51
        },
        {
          "activity" : "generateValidationPack",
          "start" : 109,
          "length" : 10
        }
      ]
    },
    {
      "name" : "fsh-generated/resources/StructureDefinition-Professionnel.json",
      "size" : 11012,
      "processes" : [
        {
          "activity" : "loadResources",
          "start" : 42,
          "length" : 4
        },
        {
          "activity" : "load",
          "start" : 42,
          "length" : 5
        },
        {
          "activity" : "generateSnapshots",
          "start" : 43,
          "length" : 8
        },
        {
          "activity" : "generateNarratives",
          "start" : 51,
          "length" : 177
        },
        {
          "activity" : "validate",
          "start" : 67,
          "length" : 289
        },
        {
          "activity" : "generate1",
          "start" : 75,
          "length" : 61
        },
        {
          "activity" : "generate2",
          "start" : 83,
          "length" : 131
        },
        {
          "activity" : "generate2",
          "start" : 96,
          "length" : 23
        },
        {
          "activity" : "generateValidationPack",
          "start" : 109,
          "length" : 4
        }
      ]
    },
    {
      "name" : "fsh-generated/resources/StructureDefinition-QualificationPAC.json",
      "size" : 3274,
      "processes" : [
        {
          "activity" : "loadResources",
          "start" : 42,
          "length" : 3
        },
        {
          "activity" : "load",
          "start" : 42,
          "length" : 58
        },
        {
          "activity" : "generateSnapshots",
          "start" : 43,
          "length" : 4
        },
        {
          "activity" : "generateNarratives",
          "start" : 51,
          "length" : 5
        },
        {
          "activity" : "validate",
          "start" : 67,
          "length" : 18
        },
        {
          "activity" : "validate",
          "start" : 71,
          "length" : 1
        },
        {
          "activity" : "generate1",
          "start" : 75,
          "length" : 32
        },
        {
          "activity" : "generate2",
          "start" : 83,
          "length" : 67
        },
        {
          "activity" : "generate2",
          "start" : 96,
          "length" : 21
        },
        {
          "activity" : "generateValidationPack",
          "start" : 109,
          "length" : 2
        }
      ]
    },
    {
      "name" : "fsh-generated/resources/StructureDefinition-SavoirFaire.json",
      "size" : 3710,
      "processes" : [
        {
          "activity" : "loadResources",
          "start" : 42,
          "length" : 3
        },
        {
          "activity" : "load",
          "start" : 42,
          "length" : 4
        },
        {
          "activity" : "generateNarratives",
          "start" : 51,
          "length" : 171
        },
        {
          "activity" : "validate",
          "start" : 67,
          "length" : 25
        },
        {
          "activity" : "generate1",
          "start" : 75,
          "length" : 30
        },
        {
          "activity" : "generate2",
          "start" : 83,
          "length" : 69
        },
        {
          "activity" : "generate2",
          "start" : 96,
          "length" : 16
        },
        {
          "activity" : "generateValidationPack",
          "start" : 109,
          "length" : 2
        }
      ]
    },
    {
      "name" : "fsh-generated/resources/StructureDefinition-SituationExercice.json",
      "size" : 13438,
      "processes" : [
        {
          "activity" : "loadResources",
          "start" : 42,
          "length" : 4
        },
        {
          "activity" : "load",
          "start" : 42,
          "length" : 6
        },
        {
          "activity" : "generateSnapshots",
          "start" : 43,
          "length" : 7
        },
        {
          "activity" : "generateNarratives",
          "start" : 51,
          "length" : 1497
        },
        {
          "activity" : "validate",
          "start" : 67,
          "length" : 2477
        },
        {
          "activity" : "scanForUsageStats",
          "start" : 74,
          "length" : 1
        },
        {
          "activity" : "generate1",
          "start" : 75,
          "length" : 86
        },
        {
          "activity" : "generate2",
          "start" : 83,
          "length" : 121
        },
        {
          "activity" : "generate2",
          "start" : 96,
          "length" : 31
        },
        {
          "activity" : "generateValidationPack",
          "start" : 109,
          "length" : 5
        }
      ]
    },
    {
      "name" : "fsh-generated/resources/StructureDefinition-SituationOperationnelle.json",
      "size" : 8321,
      "processes" : [
        {
          "activity" : "loadResources",
          "start" : 42,
          "length" : 3
        },
        {
          "activity" : "load",
          "start" : 42,
          "length" : 4
        },
        {
          "activity" : "generateSnapshots",
          "start" : 43,
          "length" : 5
        },
        {
          "activity" : "generateNarratives",
          "start" : 53,
          "length" : 338
        },
        {
          "activity" : "validate",
          "start" : 70,
          "length" : 562
        },
        {
          "activity" : "generate1",
          "start" : 75,
          "length" : 59
        },
        {
          "activity" : "generate2",
          "start" : 84,
          "length" : 88
        },
        {
          "activity" : "generate2",
          "start" : 96,
          "length" : 23
        },
        {
          "activity" : "generateValidationPack",
          "start" : 109,
          "length" : 5
        }
      ]
    },
    {
      "name" : "fsh-generated/resources/StructureDefinition-Specialite.json",
      "size" : 5129,
      "processes" : [
        {
          "activity" : "loadResources",
          "start" : 42,
          "length" : 3
        },
        {
          "activity" : "load",
          "start" : 42,
          "length" : 3
        },
        {
          "activity" : "generateSnapshots",
          "start" : 43,
          "length" : 3
        },
        {
          "activity" : "generateNarratives",
          "start" : 53,
          "length" : 5
        },
        {
          "activity" : "validate",
          "start" : 70,
          "length" : 20
        },
        {
          "activity" : "generate1",
          "start" : 76,
          "length" : 32
        },
        {
          "activity" : "generate2",
          "start" : 84,
          "length" : 69
        },
        {
          "activity" : "generate2",
          "start" : 96,
          "length" : 17
        },
        {
          "activity" : "generateValidationPack",
          "start" : 109,
          "length" : 2
        }
      ]
    },
    {
      "name" : "fsh-generated/resources/StructureDefinition-SurspecialiteTransversale.json",
      "size" : 2782,
      "processes" : [
        {
          "activity" : "loadResources",
          "start" : 42,
          "length" : 3
        },
        {
          "activity" : "load",
          "start" : 42,
          "length" : 4
        },
        {
          "activity" : "generateSnapshots",
          "start" : 43,
          "length" : 4
        },
        {
          "activity" : "generateNarratives",
          "start" : 53,
          "length" : 4
        },
        {
          "activity" : "validate",
          "start" : 70,
          "length" : 20
        },
        {
          "activity" : "generate1",
          "start" : 76,
          "length" : 26
        },
        {
          "activity" : "generate2",
          "start" : 84,
          "length" : 65
        },
        {
          "activity" : "generate2",
          "start" : 96,
          "length" : 16
        },
        {
          "activity" : "generateValidationPack",
          "start" : 109,
          "length" : 2
        }
      ]
    },
    {
      "name" : "fsh-generated/resources/StructureDefinition-Telecommunication.json",
      "size" : 5195,
      "processes" : [
        {
          "activity" : "loadResources",
          "start" : 42,
          "length" : 3
        },
        {
          "activity" : "load",
          "start" : 42,
          "length" : 4
        },
        {
          "activity" : "generateSnapshots",
          "start" : 43,
          "length" : 4
        },
        {
          "activity" : "generateNarratives",
          "start" : 53,
          "length" : 511
        },
        {
          "activity" : "validate",
          "start" : 70,
          "length" : 798
        },
        {
          "activity" : "generate1",
          "start" : 76,
          "length" : 37
        },
        {
          "activity" : "generate2",
          "start" : 84,
          "length" : 51
        },
        {
          "activity" : "generate2",
          "start" : 96,
          "length" : 18
        },
        {
          "activity" : "generateValidationPack",
          "start" : 109,
          "length" : 1
        }
      ]
    },
    {
      "name" : "fsh-generated/resources/ValueSet-DESCNonQualifiant-vs.json",
      "size" : 507,
      "processes" : [
        {
          "activity" : "loadResources",
          "start" : 42,
          "length" : 3
        },
        {
          "activity" : "load",
          "start" : 42,
          "length" : 4
        },
        {
          "activity" : "generateNarratives",
          "start" : 54,
          "length" : 85
        },
        {
          "activity" : "validate",
          "start" : 54,
          "length" : 1451
        },
        {
          "activity" : "generate1",
          "start" : 76,
          "length" : 13
        },
        {
          "activity" : "generate2",
          "start" : 84,
          "length" : 1009
        },
        {
          "activity" : "generateValidationPack",
          "start" : 109,
          "length" : 1
        }
      ]
    },
    {
      "name" : "fsh-generated/resources/ValueSet-capaciteSavoirFaire-vs.json",
      "size" : 517,
      "processes" : [
        {
          "activity" : "loadResources",
          "start" : 42,
          "length" : 2
        },
        {
          "activity" : "load",
          "start" : 42,
          "length" : 3
        },
        {
          "activity" : "generateNarratives",
          "start" : 54,
          "length" : 4
        },
        {
          "activity" : "validate",
          "start" : 55,
          "length" : 12
        },
        {
          "activity" : "generate1",
          "start" : 76,
          "length" : 12
        },
        {
          "activity" : "generate2",
          "start" : 85,
          "length" : 477
        }
      ]
    },
    {
      "name" : "fsh-generated/resources/ValueSet-competence-vs.json",
      "size" : 472,
      "processes" : [
        {
          "activity" : "loadResources",
          "start" : 42,
          "length" : 3
        },
        {
          "activity" : "load",
          "start" : 42,
          "length" : 5
        },
        {
          "activity" : "checkR4R4B",
          "start" : 43,
          "length" : 1
        },
        {
          "activity" : "generateNarratives",
          "start" : 54,
          "length" : 4
        },
        {
          "activity" : "validate",
          "start" : 55,
          "length" : 11
        },
        {
          "activity" : "generate1",
          "start" : 76,
          "length" : 12
        },
        {
          "activity" : "generate2",
          "start" : 85,
          "length" : 528
        },
        {
          "activity" : "generateValidationPack",
          "start" : 109,
          "length" : 1
        }
      ]
    },
    {
      "name" : "fsh-generated/resources/ValueSet-competenceExclusive-vs.json",
      "size" : 517,
      "processes" : [
        {
          "activity" : "loadResources",
          "start" : 42,
          "length" : 2
        },
        {
          "activity" : "load",
          "start" : 42,
          "length" : 3
        },
        {
          "activity" : "generateNarratives",
          "start" : 54,
          "length" : 3
        },
        {
          "activity" : "validate",
          "start" : 56,
          "length" : 10
        },
        {
          "activity" : "generate1",
          "start" : 76,
          "length" : 12
        },
        {
          "activity" : "generate2",
          "start" : 86,
          "length" : 478
        }
      ]
    },
    {
      "name" : "fsh-generated/resources/ValueSet-competenceMetier-vs.json",
      "size" : 487,
      "processes" : [
        {
          "activity" : "loadResources",
          "start" : 42,
          "length" : 4
        },
        {
          "activity" : "load",
          "start" : 42,
          "length" : 3
        },
        {
          "activity" : "generateNarratives",
          "start" : 54,
          "length" : 3
        },
        {
          "activity" : "validate",
          "start" : 56,
          "length" : 10
        },
        {
          "activity" : "generate1",
          "start" : 76,
          "length" : 12
        },
        {
          "activity" : "generate2",
          "start" : 86,
          "length" : 480
        }
      ]
    },
    {
      "name" : "fsh-generated/resources/ValueSet-droitExerciceComplementaire-vs.json",
      "size" : 539,
      "processes" : [
        {
          "activity" : "loadResources",
          "start" : 42,
          "length" : 3
        },
        {
          "activity" : "load",
          "start" : 42,
          "length" : 3
        },
        {
          "activity" : "generateNarratives",
          "start" : 54,
          "length" : 6
        },
        {
          "activity" : "validate",
          "start" : 56,
          "length" : 12
        },
        {
          "activity" : "generate1",
          "start" : 76,
          "length" : 12
        },
        {
          "activity" : "generate2",
          "start" : 87,
          "length" : 528
        }
      ]
    },
    {
      "name" : "fsh-generated/resources/ValueSet-fonctionQualifiee-vs.json",
      "size" : 507,
      "processes" : [
        {
          "activity" : "loadResources",
          "start" : 42,
          "length" : 2
        },
        {
          "activity" : "load",
          "start" : 42,
          "length" : 3
        },
        {
          "activity" : "generateNarratives",
          "start" : 54,
          "length" : 5
        },
        {
          "activity" : "validate",
          "start" : 56,
          "length" : 10
        },
        {
          "activity" : "generate1",
          "start" : 76,
          "length" : 12
        },
        {
          "activity" : "generate2",
          "start" : 87,
          "length" : 484
        },
        {
          "activity" : "generateValidationPack",
          "start" : 109,
          "length" : 1
        }
      ]
    },
    {
      "name" : "fsh-generated/resources/ValueSet-lieuNaissance-vs.json",
      "size" : 437,
      "processes" : [
        {
          "activity" : "loadResources",
          "start" : 42,
          "length" : 3
        },
        {
          "activity" : "load",
          "start" : 42,
          "length" : 2
        },
        {
          "activity" : "checkR4R4B",
          "start" : 43,
          "length" : 1
        },
        {
          "activity" : "generateNarratives",
          "start" : 54,
          "length" : 21
        },
        {
          "activity" : "validate",
          "start" : 56,
          "length" : 79
        },
        {
          "activity" : "generate1",
          "start" : 76,
          "length" : 11
        },
        {
          "activity" : "generate2",
          "start" : 88,
          "length" : 1909
        }
      ]
    },
    {
      "name" : "fsh-generated/resources/ValueSet-orientationParticuliere-vs.json",
      "size" : 537,
      "processes" : [
        {
          "activity" : "loadResources",
          "start" : 42,
          "length" : 3
        },
        {
          "activity" : "load",
          "start" : 42,
          "length" : 6
        },
        {
          "activity" : "load-configure",
          "start" : 43,
          "length" : 1
        },
        {
          "activity" : "generateNarratives",
          "start" : 54,
          "length" : 4
        },
        {
          "activity" : "validate",
          "start" : 56,
          "length" : 10
        },
        {
          "activity" : "generate1",
          "start" : 76,
          "length" : 13
        },
        {
          "activity" : "generate2",
          "start" : 90,
          "length" : 574
        }
      ]
    },
    {
      "name" : "fsh-generated/resources/ValueSet-paysNaissance-vs.json",
      "size" : 455,
      "processes" : [
        {
          "activity" : "loadResources",
          "start" : 42,
          "length" : 2
        },
        {
          "activity" : "load",
          "start" : 42,
          "length" : 4
        },
        {
          "activity" : "scan",
          "start" : 43,
          "length" : 1
        },
        {
          "activity" : "generateNarratives",
          "start" : 54,
          "length" : 11
        },
        {
          "activity" : "validate",
          "start" : 56,
          "length" : 11
        },
        {
          "activity" : "generate1",
          "start" : 76,
          "length" : 13
        },
        {
          "activity" : "generate2",
          "start" : 90,
          "length" : 694
        },
        {
          "activity" : "generateValidationPack",
          "start" : 109,
          "length" : 1
        }
      ]
    },
    {
      "name" : "fsh-generated/resources/ValueSet-paysNationalite-vs.json",
      "size" : 584,
      "processes" : [
        {
          "activity" : "loadResources",
          "start" : 42,
          "length" : 3
        },
        {
          "activity" : "load",
          "start" : 42,
          "length" : 4
        },
        {
          "activity" : "generateNarratives",
          "start" : 54,
          "length" : 3
        },
        {
          "activity" : "validate",
          "start" : 56,
          "length" : 12
        },
        {
          "activity" : "generate1",
          "start" : 76,
          "length" : 12
        },
        {
          "activity" : "generate2",
          "start" : 91,
          "length" : 725
        }
      ]
    },
    {
      "name" : "fsh-generated/resources/ValueSet-profession-vs.json",
      "size" : 700,
      "processes" : [
        {
          "activity" : "loadResources",
          "start" : 42,
          "length" : 2
        },
        {
          "activity" : "load",
          "start" : 42,
          "length" : 3
        },
        {
          "activity" : "generateNarratives",
          "start" : 54,
          "length" : 8
        },
        {
          "activity" : "validate",
          "start" : 56,
          "length" : 14
        },
        {
          "activity" : "generate1",
          "start" : 76,
          "length" : 14
        },
        {
          "activity" : "generate2",
          "start" : 92,
          "length" : 134
        }
      ]
    },
    {
      "name" : "fsh-generated/resources/ValueSet-professionCategorieSocioProfessionnelle-vs.json",
      "size" : 633,
      "processes" : [
        {
          "activity" : "loadResources",
          "start" : 42,
          "length" : 3
        },
        {
          "activity" : "load",
          "start" : 42,
          "length" : 3
        },
        {
          "activity" : "generateNarratives",
          "start" : 54,
          "length" : 5
        },
        {
          "activity" : "validate",
          "start" : 56,
          "length" : 10
        },
        {
          "activity" : "generate1",
          "start" : 76,
          "length" : 12
        },
        {
          "activity" : "generate2",
          "start" : 92,
          "length" : 63
        },
        {
          "activity" : "generateValidationPack",
          "start" : 109,
          "length" : 1
        }
      ]
    },
    {
      "name" : "fsh-generated/resources/ValueSet-qualificationPAC-vs.json",
      "size" : 502,
      "processes" : [
        {
          "activity" : "loadResources",
          "start" : 42,
          "length" : 2
        },
        {
          "activity" : "load",
          "start" : 42,
          "length" : 3
        },
        {
          "activity" : "checkR4R4B",
          "start" : 43,
          "length" : 1
        },
        {
          "activity" : "generateNarratives",
          "start" : 54,
          "length" : 3
        },
        {
          "activity" : "validate",
          "start" : 56,
          "length" : 9
        },
        {
          "activity" : "generate1",
          "start" : 76,
          "length" : 13
        },
        {
          "activity" : "generate2",
          "start" : 92,
          "length" : 669
        }
      ]
    },
    {
      "name" : "fsh-generated/resources/ValueSet-role-vs.json",
      "size" : 565,
      "processes" : [
        {
          "activity" : "loadResources",
          "start" : 42,
          "length" : 3
        },
        {
          "activity" : "load",
          "start" : 42,
          "length" : 3
        },
        {
          "activity" : "generateNarratives",
          "start" : 54,
          "length" : 9
        },
        {
          "activity" : "validate",
          "start" : 56,
          "length" : 14
        },
        {
          "activity" : "generate1",
          "start" : 76,
          "length" : 13
        },
        {
          "activity" : "generate2",
          "start" : 93,
          "length" : 261
        }
      ]
    },
    {
      "name" : "fsh-generated/resources/ValueSet-sexe-vs.json",
      "size" : 573,
      "processes" : [
        {
          "activity" : "loadResources",
          "start" : 42,
          "length" : 2
        },
        {
          "activity" : "load",
          "start" : 42,
          "length" : 3
        },
        {
          "activity" : "generateNarratives",
          "start" : 54,
          "length" : 7
        },
        {
          "activity" : "validate",
          "start" : 56,
          "length" : 11
        },
        {
          "activity" : "generate1",
          "start" : 76,
          "length" : 13
        },
        {
          "activity" : "generate2",
          "start" : 93,
          "length" : 50
        },
        {
          "activity" : "generateValidationPack",
          "start" : 109,
          "length" : 1
        }
      ]
    },
    {
      "name" : "fsh-generated/resources/ValueSet-specialite-vs.json",
      "size" : 488,
      "processes" : [
        {
          "activity" : "loadResources",
          "start" : 42,
          "length" : 3
        },
        {
          "activity" : "load",
          "start" : 42,
          "length" : 3
        },
        {
          "activity" : "generateNarratives",
          "start" : 54,
          "length" : 7
        },
        {
          "activity" : "validate",
          "start" : 56,
          "length" : 10
        },
        {
          "activity" : "generate1",
          "start" : 76,
          "length" : 12
        },
        {
          "activity" : "generate2",
          "start" : 93,
          "length" : 671
        }
      ]
    },
    {
      "name" : "fsh-generated/resources/ValueSet-surspecialiteTransversale-vs.json",
      "size" : 549,
      "processes" : [
        {
          "activity" : "loadResources",
          "start" : 42,
          "length" : 3
        },
        {
          "activity" : "load",
          "start" : 42,
          "length" : 5
        },
        {
          "activity" : "checkR4R4B",
          "start" : 43,
          "length" : 1
        },
        {
          "activity" : "generateNarratives",
          "start" : 54,
          "length" : 3
        },
        {
          "activity" : "validate",
          "start" : 56,
          "length" : 9
        },
        {
          "activity" : "generate1",
          "start" : 76,
          "length" : 14
        },
        {
          "activity" : "generate2",
          "start" : 94,
          "length" : 490
        }
      ]
    },
    {
      "name" : "fsh-generated/resources/ValueSet-typeProfession-vs.json",
      "size" : 488,
      "processes" : [
        {
          "activity" : "loadResources",
          "start" : 42,
          "length" : 2
        },
        {
          "activity" : "load",
          "start" : 42,
          "length" : 5
        },
        {
          "activity" : "generateNarratives",
          "start" : 54,
          "length" : 4
        },
        {
          "activity" : "validate",
          "start" : 56,
          "length" : 9
        },
        {
          "activity" : "generate1",
          "start" : 76,
          "length" : 14
        },
        {
          "activity" : "generate2",
          "start" : 94,
          "length" : 45
        },
        {
          "activity" : "generateValidationPack",
          "start" : 109,
          "length" : 1
        }
      ]
    },
    {
      "name" : "fsh-generated/resources/ValueSet-typeRole-vs.json",
      "size" : 466,
      "processes" : [
        {
          "activity" : "loadResources",
          "start" : 42,
          "length" : 4
        },
        {
          "activity" : "load",
          "start" : 42,
          "length" : 3
        },
        {
          "activity" : "generateNarratives",
          "start" : 54,
          "length" : 3
        },
        {
          "activity" : "validate",
          "start" : 56,
          "length" : 10
        },
        {
          "activity" : "generate1",
          "start" : 76,
          "length" : 12
        },
        {
          "activity" : "generate2",
          "start" : 94,
          "length" : 46
        }
      ]
    }
  ]
}
